rstdiary/__init__.py
rstdiary/rstdiary.py
rstdiary/templates/atom.xml
rstdiary/templates/page.html
rstdiary/tests/__init__.py
rstdiary/tests/test_rstdiary.py
rstdiary-3.0.dist-info/LICENSE
rstdiary-3.0.dist-info/METADATA
rstdiary-3.0.dist-info/WHEEL
rstdiary-3.0.dist-info/entry_points.txt
rstdiary-3.0.dist-info/top_level.txt
rstdiary-3.0.dist-info/RECORD
