Metadata-Version: 2.1
Name: rstdiary
Version: 3.0
Summary: Create static HTML diary from single RST input
Home-page: https://github.com/ianw/rstdiary
Author: Ian Wienand
Author-email: ian@wienand.org
License: MIT License
Classifier: Development Status :: 5 - Production/Stable
Classifier: Intended Audience :: End Users/Desktop
Classifier: License :: OSI Approved :: MIT License
Classifier: Topic :: Office/Business :: News/Diary
Classifier: Programming Language :: Python :: 3
License-File: LICENSE
Requires-Dist: docutils
Requires-Dist: Jinja2 >=2.4
